CMakeLists.txt
MANIFEST.in
README.md
pyproject.toml
setup.py
path_tracing/__init__.py
path_tracing/wrapper.py
path_tracing.egg-info/PKG-INFO
path_tracing.egg-info/SOURCES.txt
path_tracing.egg-info/dependency_links.txt
path_tracing.egg-info/not-zip-safe
path_tracing.egg-info/requires.txt
path_tracing.egg-info/top_level.txt
src/CMakeLists.txt
src/path_tracer.h
src/path_tracer_impl.h
src/pybind.cpp
src/cpu/CMakeLists.txt
src/cpu/bvhtree.h
src/cpu/camera.h
src/cpu/cpu_path_tracer_impl.cpp
src/cpu/cpu_path_tracer_impl.h
src/cpu/defs.h
src/cpu/hit.h
src/cpu/image.h
src/cpu/material.h
src/cpu/object.h
src/cpu/ray.h
src/cpu/scene.h
src/cpu/texture.h
src/cpu/timer.h
src/cuda/CMakeLists.txt
src/cuda/array.h
src/cuda/camera.h
src/cuda/cuda_path_tracer_impl.cpp
src/cuda/cuda_path_tracer_impl.h
src/cuda/defs.h
src/cuda/material.h
src/cuda/object.h
src/cuda/path_tracer_kernel.cu
src/cuda/path_tracer_kernel.cuh
src/cuda/ray.h
src/cuda/scene.h
src/cuda/texture.h
src/cuda/vec.h
third_party/CMakeLists.txt
third_party/pybind11.cmake
third_party/tinyobjloader.cmake
third_party/pybind11/.appveyor.yml
third_party/pybind11/.clang-format
third_party/pybind11/.clang-tidy
third_party/pybind11/.cmake-format.yaml
third_party/pybind11/.git
third_party/pybind11/.gitignore
third_party/pybind11/.pre-commit-config.yaml
third_party/pybind11/.readthedocs.yml
third_party/pybind11/CMakeLists.txt
third_party/pybind11/LICENSE
third_party/pybind11/MANIFEST.in
third_party/pybind11/README.rst
third_party/pybind11/noxfile.py
third_party/pybind11/pyproject.toml
third_party/pybind11/setup.cfg
third_party/pybind11/setup.py
third_party/pybind11/.github/CODEOWNERS
third_party/pybind11/.github/CONTRIBUTING.md
third_party/pybind11/.github/dependabot.yml
third_party/pybind11/.github/labeler.yml
third_party/pybind11/.github/labeler_merged.yml
third_party/pybind11/.github/pull_request_template.md
third_party/pybind11/.github/ISSUE_TEMPLATE/bug-report.md
third_party/pybind11/.github/ISSUE_TEMPLATE/config.yml
third_party/pybind11/.github/ISSUE_TEMPLATE/feature-request.md
third_party/pybind11/.github/ISSUE_TEMPLATE/question.md
third_party/pybind11/.github/workflows/ci.yml
third_party/pybind11/.github/workflows/configure.yml
