Metadata-Version: 2.1
Name: path-tracing
Version: 0.0.1
Summary: A fast path tracing renderer
Home-page: https://github.com/li-plus/path-tracing
Author: Jiahao Li
Author-email: liplus17@163.com
Maintainer: Jiahao Li
Maintainer-email: liplus17@163.com
License: MIT
Keywords: path tracing,ray tracing,rendering,computer graphics
Platform: UNKNOWN
Classifier: Development Status :: 3 - Alpha
Classifier: Intended Audience :: Science/Research
Classifier: Topic :: Multimedia :: Graphics :: 3D Rendering
Classifier: License :: OSI Approved :: MIT License
Classifier: Programming Language :: Python :: 3
Requires-Python: >=3.6
Provides-Extra: dev
